kedro_alpiq/__init__.py
kedro_alpiq-0.0.1.dist-info/LICENSE
kedro_alpiq-0.0.1.dist-info/METADATA
kedro_alpiq-0.0.1.dist-info/WHEEL
kedro_alpiq-0.0.1.dist-info/top_level.txt
kedro_alpiq-0.0.1.dist-info/RECORD
