Metadata-Version: 2.1
Name: kedro-alpiq
Version: 0.0.1
Summary: A Public stub for kedro-alpiq by Alpiq
Home-page: https://alpiq.com
Author: Lucas Jamar
Author-email: lucas.jamar@alpiq.com
License: Commercial
Platform: UNKNOWN
Classifier: Programming Language :: Python :: 3
